{
  "topic": "sarjapur road",
  "competitor_coverage": {
    "magicbricks.com": 9,
    "nobroker.in": 8,
    "housing.com": 1,
    "99acres.com": 9
  },
  "raw_results": [
    {
      "query": "Sarjapur Road property",
      "results": [
        {
          "position": 1,
          "title": "Property in Sarjapur Road, Bangalore",
          "link": "https://www.99acres.com/property-in-sarjapur-road-bangalore-east-ffid",
          "snippet": "Book your 2 BHK apartment in Sarjapur Road, Bangalore East at a price ranging from Rs. 80.56 Lac to Rs. 96.06 Lac. The Global Edifice The Clan hosts exclusively ..."
        },
        {
          "position": 2,
          "title": "Property in Sarjapur Road, Bangalore",
          "link": "https://www.magicbricks.com/property-for-sale-in-sarjapur-road-bangalore-pppfs",
          "snippet": "You can get a property for sale in Sarjapur Road at a price range of \u20b945.3 Lac - \u20b915.30 Cr. Some of the popular localities around Sarjapur Road are C V Raman ..."
        },
        {
          "position": 3,
          "title": "Properties in Sarjapur Road for Sale",
          "link": "https://www.jllhomes.co.in/properties-for-sale-in-sarjapur-road-bengaluru",
          "snippet": "Explore premium properties in Sarjapur Road for sale. Find verified flats and villas with trusted insights from JLL Homes."
        },
        {
          "position": 4,
          "title": "Properties for Sale in Sarjapur Road",
          "link": "https://www.bhavishahomes.com/properties-in-sarjapur-road",
          "snippet": "Premium properties in Sarjapur Road with Bhavisha Home. We provide the best properties for sale in Sarjapur Road with top amenities. Enquire now!"
        },
        {
          "position": 5,
          "title": "Sarjapur Road - Real Estate Properties in Bangalore",
          "link": "https://www.housingman.com/bangalore/real-estate-properties-in-sarjapur-road-bangalore",
          "snippet": "Top Projects in Sarjapur Road ; Vaswani Reserve \u00b7 4 BHK; 4000 - 4000 Sqft ; Mana Karmel Phase 2 \u00b7 2 BHK; 1028 - 1080 Sqft ; Astro Rosewood Regency \u00b7 3, 4 BHK; 1681 - ..."
        },
        {
          "position": 6,
          "title": "Property Rates in Sarjapur Road, Bengaluru - 2026 - Housing",
          "link": "https://housing.com/price-trends/property-rates-for-buy-in-sarjapur_road_bengaluru-P1zr02w1owlhq796j",
          "snippet": "Starting price of properties in Sarjapur Road is Rs. 2,500 per sqft and the average price of properties in Sarjapur Road is Rs. 11,052 per sqft. Price trend ..."
        },
        {
          "position": 7,
          "title": "Flats for Sale in Sarjapur Bangalore | Apartments in ...",
          "link": "https://www.nobroker.in/flats-for-sale-in-sarjapur_bangalore",
          "snippet": "104 - Flats for Sale in Sarjapur Bangalore | Apartments for Sale in Sarjapur Bangalore ; 4+ BHK Apartment In Arvind Forest Trails For Sale In Chichuranganapalli ..."
        },
        {
          "position": 8,
          "title": "Property for sale in Sarjapur Road Bangalore",
          "link": "https://www.360realtors.com/property-in-sarjapur-road-bangalore-lid-218",
          "snippet": "Looking for property in Sarjapur Road Bangalore. Find all the details of residential and commercial India properties with its specifications & related ..."
        },
        {
          "position": 9,
          "title": "2 BHK Property in Sarjapur Road, Bangalore",
          "link": "https://www.99acres.com/2-bhk-property-in-sarjapur-road-bangalore-east-ffid",
          "snippet": "The project offers 2 BHK apartments in Sarjapur Road, Bangalore East. These apartments have a super built-up area, ranging from 1180.0 sq. ft. to 1205.0 sq. ft."
        },
        {
          "position": 10,
          "title": "Sarjapur Road, Bangalore",
          "link": "https://www.magicbricks.com/Sarjapur-Road-in-Bangalore-Overview",
          "snippet": "10% properties for Sale in Sarjapur Road lie in range of \u20b91.2Cr - \u20b91.4Cr while 10% properties for Sale lie in range of \u20b91Cr - \u20b91.2Cr. 3 BHK is the most common ..."
        }
      ]
    },
    {
      "query": "Sarjapur Road apartments",
      "results": [
        {
          "position": 1,
          "title": "Apartments in Sarjapur Road, Bangalore - 2191+ Flats for ...",
          "link": "https://www.99acres.com/flats-in-sarjapur-road-bangalore-east-ffid",
          "snippet": "Book your 2 BHK apartment in Sarjapur Road, Bangalore East at a price ranging from Rs. 80.56 Lac to Rs. 96.06 Lac. The Global Edifice The Clan hosts exclusively ..."
        },
        {
          "position": 2,
          "title": "5957+ Flats for Sale in Sarjapur Road, Bangalore",
          "link": "https://www.magicbricks.com/flats-in-sarjapur-road-bangalore-for-sale-pppfs",
          "snippet": "There are about 1K+ ready to move flats in Sarjapur Road starting from \u20b9 47.1 lakhs depending on BHK type. What is the price of 2 BHK flats in Sarjapur Road?"
        },
        {
          "position": 3,
          "title": "Apartments in Sarjapur Road",
          "link": "https://www.nbrgroup.in/apartments-in-sarjapur-road",
          "snippet": "NBR offers only 3 BHK flats for sale in Sarjapur Road, with pricing starting from \u20b91.54 Cr, depending on the unit type and view. Buyers considering 1 BHK, 2 BHK ..."
        },
        {
          "position": 4,
          "title": "Flats for Sale in Sarjapur Bangalore | Apartments in ...",
          "link": "https://www.nobroker.in/flats-for-sale-in-sarjapur_bangalore",
          "snippet": "3 BHK Apartment In Mana Verdant Terraces For Sale In Sarjapur Road. \u20b92.24 Cr. \u20b911,728/sq.ft. Near Winmore Academy, Jakkur Main Road, Sarjapur Road, Bangalore ..."
        },
        {
          "position": 5,
          "title": "New Apartments in Sarjapur Road",
          "link": "https://www.adarshdevelopers.com/lp/apartments-in-sarjapur-road.php",
          "snippet": "The key features of Adarsh Tropica include its beautifully landscaped courtyard for 2 BHK flats, floor planning, BDA approvals, 10+ amenities, panoramic view of ..."
        },
        {
          "position": 6,
          "title": "Flats for Sale in Sarjapur Road Bangalore",
          "link": "https://www.housingman.com/bangalore/flats-for-sale-in-sarjapur-road-bangalore",
          "snippet": "Apartments for sale in Sarjapur Road, Bangalore ; DSR Wood Winds \u00b7 3, 4 BHK Apartment in Sarjapur Road. \u20b91.01 Cr* - \u20b92.12 Cr* ; Mana Karmel Phase 2 \u00b7 2 BHK ..."
        },
        {
          "position": 7,
          "title": "Flats for Sale in Sarjapur Road, Bengaluru",
          "link": "https://www.roofandfloor.com/bengaluru/flats-for-sale-in-sarjapur-road",
          "snippet": "There are a total of 180 units of beautiful and various 2,2.5, and 3 BHK apartments spread across 2.45 acres' landscape. Every home here is designed with nature ..."
        },
        {
          "position": 8,
          "title": "Ready To Move Projects In Sarjapur Road Bangalore",
          "link": "https://www.squareyards.com/ready-to-move-projects-in-sarjapur-road-bangalore",
          "snippet": "Ready to Move Projects in Sarjapur Road, Bangalore ; Prestige Eden Gardens \u00b7 Price On Request ; Purva Mithra Apoorva Elite \u00b7 Starting From\u20b9 40.74 Lac \u00b7 No. of Units ..."
        },
        {
          "position": 9,
          "title": "1559+ Flats for Rent in Sarjapur Road, Bangalore",
          "link": "https://www.99acres.com/flats-for-rent-in-sarjapur-road-bangalore-east-ffid",
          "snippet": "A 3 bhk flat for rent in sarjapur road close to all basic civic amenities is available for just 63,000 in prestige city avalon park, bangalore east."
        }
      ]
    },
    {
      "query": "Sarjapur Road 2bhk for sale",
      "results": [
        {
          "position": 1,
          "title": "781+ 2 BHK Flats in Sarjapur Road, Bangalore",
          "link": "https://www.99acres.com/2-bhk-flats-in-sarjapur-road-bangalore-east-ffid",
          "snippet": "2 BHK Flats in Sarjapur Road, Bangalore ; Keya The Urban Forest \u00b7 2 BHK Apartment. \u20b91.63 - 1.71 Cr. 3 BHK Apartment. \u20b92.08 - 2.38 Cr. 4 BHK Apartment. \u20b92.86 - ..."
        },
        {
          "position": 2,
          "title": "2 BHK Flats in Sarjapur Road, Bangalore",
          "link": "https://www.magicbricks.com/2-bhk-flats-in-sarjapur-road-bangalore-for-sale-pppfs",
          "snippet": "Find your ideal 2 BHK flat in Sarjapur Road within the price range of \u20b966 Lac - \u20b92.12 Cr. Choose from 1005+ resale flats, 1016+ ready-to-move flats, and 753+ ..."
        },
        {
          "position": 3,
          "title": "2 BHK Flats For Sale in Sarjapur Main Road , Bangalore",
          "link": "https://www.nobroker.in/2bhk-flats-for-sale-in-sarjapur_main_road_bangalore",
          "snippet": "338+ 2 BHK Apartments/flats available for sale in Sarjapur Main Road, , Bangalore within your budget & no brokerage. Contact property owners directly for 2 ..."
        },
        {
          "position": 4,
          "title": "2 BHK in Sarjapur Road | 2 BHK Flats for Sale",
          "link": "https://www.bhavishahomes.com/2-bhk-in-sarjapur-road",
          "snippet": "Bhavisha Homes 2 BHK flats for sale in Sarjapur Road come with amenities like a clubhouse, gym, landscaped gardens, play areas, and more to enhance your living ..."
        },
        {
          "position": 5,
          "title": "2 BHK Flats/Apartments for Sale in Sarjapur Road, Bangalore",
          "link": "https://nambiarbuilders.com/2-bhk-flats-sarjapur-road/",
          "snippet": "Nambiar Builders offers 2 BHK apartments for sale in Sarjapur Road that combine modern living with quality construction. These spacious homes ..."
        },
        {
          "position": 6,
          "title": "5 Flats & Apartments for Sale in Sarjapur Road",
          "link": "https://www.olx.in/sarjapur-road_g5457308/for-sale-houses-apartments_c1725/q-2-bhk-for-sale",
          "snippet": "Flats for Sale: Buy & Sell Houses, Apartments and Flats in Sarjapur Road \u00b7 2 BHK - 2 bath - 1160 sqft \u00b7 2 BHK Corner road complete building 4 Floors for sale \u00b7 2 ..."
        },
        {
          "position": 7,
          "title": "2 BHK Flats for Sale In Sarjapur Road, Bangalore",
          "link": "https://beegru.com/s/2-bhk-flats-for-sale-in-sarjapur-road-bangalore",
          "snippet": "Explore premium 2 BHK flats for sale in Sarjapur Road. Experience modern design, secure neighborhoods, and quality amenities for urban living."
        },
        {
          "position": 8,
          "title": "2 BHK Property in Sarjapur Road, Bangalore",
          "link": "https://www.99acres.com/2-bhk-property-in-sarjapur-road-bangalore-east-ffid",
          "snippet": "The project offers 2 BHK apartments in Sarjapur Road, Bangalore East. These apartments have a super built-up area, ranging from 1180.0 sq. ft. to 1205.0 sq. ft."
        },
        {
          "position": 9,
          "title": "2 BHK Flats For Sale in Sarjapur , Bangalore",
          "link": "https://www.nobroker.in/2bhk-flats-for-sale-in-sarjapur_bangalore",
          "snippet": "2 BHK Apartment In Confident Orion Apartment For Sale In Sarjapur \u00b7 83 Lacs. \u20b97,131/sq.ft ; 2 BHK Apartment In Ultra Codename Sarjapur For Sale In Sarjapur \u00b7 1.50 ..."
        },
        {
          "position": 10,
          "title": "85+ 2 BHK Flats For Sale in Sarjapur Road, Bangalore",
          "link": "https://www.squareyards.com/sale/2-bhk-for-sale-in-sarjapur-road-bangalore",
          "snippet": "Find over 85+ of 2 BHK Flats for sale in Sarjapur Road, Bangalore only on Squareyards.com. Buy 2 BHK Apartments / Flats in Sarjapur Road, ..."
        }
      ]
    },
    {
      "query": "buy flat in Sarjapur Road",
      "results": [
        {
          "position": 1,
          "title": "Apartments in Sarjapur Road, Bangalore - 2191+ Flats for ...",
          "link": "https://www.99acres.com/flats-in-sarjapur-road-bangalore-east-ffid",
          "snippet": "Apartments in Sarjapur Road, Bangalore ; Roach Cicada \u00b7 \u20b92.75 - 3.12 Cr. 4 BHK Apartment. \u20b93.84 Cr ; Keya The Urban Forest \u00b7 \u20b91.63 - 1.71 Cr. 3 BHK Apartment. \u20b92.08 ..."
        },
        {
          "position": 2,
          "title": "5957+ Flats for Sale in Sarjapur Road, Bangalore",
          "link": "https://www.magicbricks.com/flats-in-sarjapur-road-bangalore-for-sale-pppfs",
          "snippet": "The price of a flat in Sarjapur Road is between \u20b9 46.2 lakhs - \u20b9 12.03 Cr. Is it worth it to buy a flat in Sarjapur Road, Bangalore? Due to its great ..."
        },
        {
          "position": 3,
          "title": "Flats for Sale in Sarjapur Bangalore | Apartments in ...",
          "link": "https://www.nobroker.in/flats-for-sale-in-sarjapur_bangalore",
          "snippet": "104 - Flats for Sale in Sarjapur Bangalore | Apartments for Sale in Sarjapur Bangalore ; 4+ BHK Apartment In Arvind Forest Trails For Sale In Chichuranganapalli ..."
        },
        {
          "position": 4,
          "title": "Flats for Sale in Sarjapur Road Bangalore",
          "link": "https://www.housingman.com/bangalore/flats-for-sale-in-sarjapur-road-bangalore",
          "snippet": "DSR Wood Winds \u00b7 3, 4 BHK Apartment in Sarjapur Road. \u20b91.01 Cr* - \u20b92.12 Cr* ; Mana Karmel Phase 2 \u00b7 2 BHK Apartment in Sarjapur Road. \u20b940.09 L* - \u20b942.12 L*."
        },
        {
          "position": 5,
          "title": "Flats for Sale in Sarjapur Road, Bengaluru",
          "link": "https://www.roofandfloor.com/bengaluru/flats-for-sale-in-sarjapur-road",
          "snippet": "The cost of an flat in Sarjapur Road ranges from 16.50 L - 4.69 Cr *. How much does it cost to buy a 1 bhk flat in Sarjapur Road? The average cost of 1 bhk ..."
        },
        {
          "position": 6,
          "title": "Buy Luxury Apartments/Flats for Sale in Sarjapur Road",
          "link": "https://www.nbrgroup.in/apartments-for-sale-sarjapur-road/",
          "snippet": "Affordable Apartments (1.64 Cr - 1.65 Cr): Ideal for budget-conscious buyers, our 1 BHK and 2 BHK apartments for sale in Sarjapur Road provide excellent value ..."
        },
        {
          "position": 7,
          "title": "Properties in Sarjapur Road for Sale",
          "link": "https://www.jllhomes.co.in/properties-for-sale-in-sarjapur-road-bengaluru",
          "snippet": "Explore premium properties in Sarjapur Road for sale. Find verified flats and villas with trusted insights from JLL Homes."
        },
        {
          "position": 8,
          "title": "Buying flat in Sarjapur road is good choice? : r/bangalore",
          "link": "https://www.reddit.com/r/bangalore/comments/vu2r7q/buying_flat_in_sarjapur_road_is_good_choice/",
          "snippet": "I saw some of the flats in Suncity Gloria, Ahad Euphoria, Concorde Amber like area are cheaper. Around 65-75L you get a 2bhk, ready to move in."
        },
        {
          "position": 9,
          "title": "27 Flats & Apartments for Sale in Sarjapur Road",
          "link": "https://www.olx.in/en-in/sarjapur-road_g5457308/for-sale-houses-apartments_c1725",
          "snippet": "Flats for Sale: Buy & Sell Houses, Apartments and Flats in Sarjapur Road. Explore flats for sale in Sarjapur Road in the price range of \u20b910,000 - \u20b9180 Crores."
        },
        {
          "position": 10,
          "title": "Ready to Move Flats in Sarjapur Road, Bangalore",
          "link": "https://www.99acres.com/ready-to-move-flats-apartments-in-sarjapur-road-bangalore-east-ffid",
          "snippet": "Find Ready to Move Flats in Sarjapur Road, Bangalore on 99acres.com, India's No.1 Real Estate Portal. Explore 1/2/3/4 BHK Ready to Move Apartments in ..."
        }
      ]
    },
    {
      "query": "Sarjapur Road real estate review",
      "results": [
        {
          "position": 1,
          "title": "Ratings & Reviews of Sarjapur Road, Bangalore",
          "link": "https://www.99acres.com/sarjapur-road-bangalore-east-reviews-and-ratings-wrffid",
          "snippet": "The area is very good and safe for living in. The closest market is nearly 1km. Police do patrol every night so we don't have any fear of Thieves. The ..."
        },
        {
          "position": 2,
          "title": "How is living in Sarjapur : r/bangalore",
          "link": "https://www.reddit.com/r/bangalore/comments/1f6ucsr/how_is_living_in_sarjapur/",
          "snippet": "It's a dust bowl and too far from everywhere airport, mg road, commercial street, etc. Also, not sure if the villa will have a reliable water source."
        },
        {
          "position": 3,
          "title": "Sarjapur Road Reviews & Ratings",
          "link": "https://www.magicbricks.com/real-estate-property-reviews/Sarjapur-Road-in-Bangalore",
          "snippet": "It is a Nice Locality. Serenity Layout is very calm and peaceful. It is connected well to all nearby IT tech parks and major city areas like HSR, Kormangala, ..."
        },
        {
          "position": 4,
          "title": "Top 8 Reasons to Invest in 2 & 3 BHK in Sarjapur Road",
          "link": "https://www.theceyone.com/blog/sarjapur-road-2-3-bhk-apartments",
          "snippet": "Sarjapur Road is emerging as one of Bengaluru's strongest residential corridors, offering excellent connectivity, top schools, modern lifestyle amenities, and ..."
        },
        {
          "position": 5,
          "title": "How is the Place Sarjapur Road to Live",
          "link": "https://www.nobroker.in/forum/how-is-the-place-sarjapur-road-to-live-2/",
          "snippet": "Sarjapur is a very polished and well-developed area. You can reach any destination from there easily. It has good connectivity with a lot of ..."
        },
        {
          "position": 6,
          "title": "Why Sarjapur Road Excels in Bangalore's Real Estate ...",
          "link": "https://www.homes247.in/blogs/sarjapur-road-evergreen-realty-market-bangalore-1583",
          "snippet": "This development is celebrated for its stylish design and high-quality construction, earning glowing reviews in Mana Capitol reviews. To ..."
        },
        {
          "position": 7,
          "title": "Best Real Estate Projects in Sarjapur, Bangalore",
          "link": "https://www.mouthshut.com/projects/bangalore/sarjapur",
          "snippet": "73 Reviews \u00b7 Ahad Euphoria. Sarjapur Road, Bangalore. 1,2,3,4 BHK Apartments. Kumari Oakville Villas Photos. Ready to Move. 2.29. Price On Request \u00b7 34% \u00b7 22 ..."
        },
        {
          "position": 8,
          "title": "Is it a good option to buy a Villa in Sarjapur Road. ...",
          "link": "https://www.quora.com/Is-it-a-good-option-to-buy-a-Villa-in-Sarjapur-Road-What-are-the-pros-and-cons-of-it",
          "snippet": "Sarjapur road is a very nice area for investing in villas, First visit there and find all the villa's project, after that each and every things ..."
        }
      ]
    },
    {
      "query": "living in Sarjapur Road",
      "results": [
        {
          "position": 1,
          "title": "How is living in Sarjapur : r/bangalore",
          "link": "https://www.reddit.com/r/bangalore/comments/1f6ucsr/how_is_living_in_sarjapur/",
          "snippet": "Sarjapur road has everything but inside areas feels isolated some how. Feels like you are disconnected from Bangalore."
        },
        {
          "position": 2,
          "title": "Advantages and Disadvantages of living in Sarjapur - KOTS",
          "link": "https://www.kots.world/blog/advanatages-and-disadvantages-of-living-in-sarjapur",
          "snippet": "Today it is the preference of working professionals and families too to reside in Sarjapur, an up-and-coming region of Bangalore."
        },
        {
          "position": 3,
          "title": "Why Sarjapur Road is One of the Best Places to Live in ...",
          "link": "https://www.magicbricks.com/blog/sarjapur-road-bangalore-best-place-to-live-invest/144907.html",
          "snippet": "Pros and Cons of living in Sarjapur Road ; High-end schools, healthcare, gyms, and parks. Water supply issues in select pockets ; Modern ..."
        },
        {
          "position": 4,
          "title": "Living in the Heart of Bangalore's Growth: The Sarjapur ...",
          "link": "https://www.manaprojects.com/blog/living-in-the-heart-of-bangalore-growth-sarjapur-advantage/",
          "snippet": "Sarjapur Road offers a plethora of recreational and lifestyle amenities that enhance the living experience for its residents. Shopping and Entertainment: The ..."
        },
        {
          "position": 5,
          "title": "Sarjapur Road: Decoding Bangalore's Premier Hub for ...",
          "link": "https://hmconstructions.com/sarjapur-road-decoding-bangalores-premier-hub-for-living-and-investment/",
          "snippet": "Sarjapur Road offers a unique blend of excellent connectivity to major IT hubs, a complete social infrastructure with top schools and hospitals, and strong ..."
        },
        {
          "position": 6,
          "title": "Is Sarjapur Road a Good Place to Live in Bengaluru?",
          "link": "https://www.birlaevara.org.in/sarjapur-road/is-sarjapur-road-a-good-place-to-live.html",
          "snippet": "Sarjapur Road is a good place to live in Bangalore, with its elite housing projects and excellent services. It is known for its easy connectivity."
        },
        {
          "position": 7,
          "title": "Top 8 Reasons to Invest in 2 & 3 BHK in Sarjapur Road",
          "link": "https://www.theceyone.com/blog/sarjapur-road-2-3-bhk-apartments",
          "snippet": "Why 2 & 3 BHK apartments in Sarjapur Road are a smart choice. IT hubs, metro growth, top schools, lifestyle benefits, and appreciation potential."
        },
        {
          "position": 8,
          "title": "The Rise of Sarjapur Road as a Real Estate Hotspot",
          "link": "https://bren.com/the-rise-of-sarjapur-road-as-a-real-estate-hotspot-spotlight-on-kasavanahalli.php",
          "snippet": "Discover why Sarjapur Road is a booming real estate hotspot. Learn about Kasavanahalli's strategic location, growing amenities, and Bren Zahara's luxury ..."
        },
        {
          "position": 9,
          "title": "Top 8 gated communities is Sarjapur Road, Bangalore ...",
          "link": "https://mygate.com/blog/neighbourhood/gated-communities-in-sarjapur-road/",
          "snippet": "To help you find a home best suited to your requirements, below we have listed the best-gated community for rent in and around Sarjapur Road."
        }
      ]
    },
    {
      "query": "Which part of Bangalore is Sarjapur Road?",
      "results": [
        {
          "position": 1,
          "title": "Sarjapura",
          "link": "https://en.wikipedia.org/wiki/Sarjapura",
          "snippet": "It is a hobli of Anekal taluk, Bengaluru Urban district, and is located towards the southeast of Bangalore. It is one of the industrial areas in Anekal taluk, ..."
        },
        {
          "position": 2,
          "title": "Is sarjapur part of Bangalore - Bengaluru",
          "link": "https://www.reddit.com/r/bangalore/comments/1gt8ygi/is_sarjapur_part_of_bangalore/",
          "snippet": "It is now. But depends on what you define Bangalore as. If you ask oldies in Jayanagar, they will still refer to the areas between Chamrajpete and Malleshwaram ..."
        },
        {
          "position": 3,
          "title": "Sarjapur, Bangalore: Map, Photo, Video, Price Trends ...",
          "link": "https://www.magicbricks.com/Sarjapur-in-Bangalore-Overview",
          "snippet": "Located on the south-east part of Bangalore, Sarjapur is one of the prime residential and commercial hotspots of Bangalore with high-end social ..."
        },
        {
          "position": 4,
          "title": "Sarjapur Road, Bangalore: Location & Surrounding Areas 2025",
          "link": "https://www.nambiardistrict25.info/location/sarjapur-road-bangalore-location-and-surrounding-areas-2025.html",
          "snippet": "Sarjapur Road runs southwest from the Outer Ring Road (ORR) in Carmelaram down through Kaikondrahalli to HSR Layout and beyond. Its central spot makes it a ..."
        },
        {
          "position": 5,
          "title": "Everything you need to know about Sarjapur Road, ...",
          "link": "https://mygate.com/blog/neighbourhood/all-about-gated-communities-in-sarjapur-road-bangalore/",
          "snippet": "Sarjapur, situated in Bangalore's southeast, is an excellent area for residential and commercial activity. It has a high standard of social infrastructure."
        },
        {
          "position": 6,
          "title": "Sarjapur Road | Location, Map, Metro & Property Update ...",
          "link": "https://www.prestigeeatonpark.info/sarjapur-road/",
          "snippet": "Sarjapur Road, Bangalore, is a top residential and tech locale nestled in Southeast Bangalore. It stretches about 25 Km and is known for its ..."
        },
        {
          "position": 7,
          "title": "Locality Review: Sarjapur, Bengaluru",
          "link": "https://www.youtube.com/watch?v=LXtO6E1bvJ0",
          "snippet": "Sarjapur, situated in south-east Bengaluru, is part of the Anekal tTaluk ... Sarjapur-Road-in-Bangalore-Overview."
        },
        {
          "position": 8,
          "title": "Why Sarjapur Road is Bangalore's Premier Residential ...",
          "link": "https://www.bricksandmilestones.com/post/dream-home-in-bengaluru-its-got-to-be-sarjapur-road",
          "snippet": "Sarjapur Road is considered one of Bangalore's most strategically positioned residential corridors. The area offers seamless connectivity to major IT hubs."
        },
        {
          "position": 9,
          "title": "Sarjapur, Bangalore - Map, Pin Code, & Property Rates 2026",
          "link": "https://www.nobroker.in/locality-iq/sarjapur-bangalore-liqlt",
          "snippet": "Sarjapur PIN code is 562125. Sarjapur is conveniently located near major areas such as Sarjapur Road, Bellandur, Marathahalli, and Whitefield. As an ..."
        }
      ]
    },
    {
      "query": "Is Sarjapura posh area in Bangalore?",
      "results": [
        {
          "position": 1,
          "title": "How is living in Sarjapur : r/bangalore",
          "link": "https://www.reddit.com/r/bangalore/comments/1f6ucsr/how_is_living_in_sarjapur/",
          "snippet": "Its much better compared to properties in north bangalore, budigere and devanahalli (in terms if city proximity) \u00b7 With time that would change as ..."
        },
        {
          "position": 2,
          "title": "Why Sarjapur Road is One of the Best Places to Live in ...",
          "link": "https://www.magicbricks.com/blog/sarjapur-road-bangalore-best-place-to-live-invest/144907.html",
          "snippet": "It is known to be a posh area due to its rapid growth, the infrastructure, its closeness to many major IT hubs and the high-end options of flats ..."
        },
        {
          "position": 3,
          "title": "Is Sarjapur a Posh Area in Bangalore? - Birla Evara",
          "link": "https://www.birlaevara.org.in/sarjapur-road/is-sarjapur-a-posh-area-in-bangalore.html",
          "snippet": "The answer to the question of whether Sarjapur is a posh area in Bangalore is an emphatic yes. It is one of the top 10 residential areas in the city."
        },
        {
          "position": 4,
          "title": "Advantages and Disadvantages of living in Sarjapur - KOTS",
          "link": "https://www.kots.world/blog/advanatages-and-disadvantages-of-living-in-sarjapur",
          "snippet": "Sarjapur is overall a very secure area, particularly in gated compounds with security firms. Having prominent schools, medical facilities, and ..."
        },
        {
          "position": 5,
          "title": "Reality of Living in Sarjapur | Bangalore - Pros & Cons",
          "link": "https://www.youtube.com/watch?v=qwe6M_dgMKM",
          "snippet": "How is Sarjapur Area Bengaluru? | Ground Reality, Water, Roads & Property Price | Near STRR. Sky Imprint [ \u0938\u094d\u0915\u093e\u0908 \u0907\u0902\u092a\u094d\u0930\u093f\u0902\u091f] \u00b7 385 views ; NRI OCI Rules: ..."
        },
        {
          "position": 6,
          "title": "Why Sarjapur Road is Bangalore's Premier Residential ...",
          "link": "https://www.bricksandmilestones.com/post/dream-home-in-bengaluru-its-got-to-be-sarjapur-road",
          "snippet": "Sarjapur Road is considered one of Bangalore's most strategically positioned residential corridors. The area offers seamless connectivity to major IT hubs."
        },
        {
          "position": 7,
          "title": "Top 10 Posh Areas in Bangalore (Best Residential Areas)",
          "link": "https://www.sobha.com/blog/posh-areas-in-bangalore/",
          "snippet": "Sarjapur Road has emerged as one of the posh areas in Bangalore, witnessing rapid development due to its proximity to major IT hubs. The area ..."
        },
        {
          "position": 8,
          "title": "Everything you need to know about Sarjapur Road, ...",
          "link": "https://mygate.com/blog/neighbourhood/all-about-gated-communities-in-sarjapur-road-bangalore/",
          "snippet": "Sarjapur, situated in Bangalore's southeast, is an excellent area for residential and commercial activity. It has a high standard of social infrastructure."
        },
        {
          "position": 9,
          "title": "How is Sarjapur Area in Bangalore",
          "link": "https://www.nobroker.in/forum/how-is-sarjapur-area-in-bangalore/",
          "snippet": "Yes it is indeed a great place to live in Bangalore. With its extensive facilities and amenities, Sarjapura is undeniably the top choice for booking a dream ..."
        }
      ]
    }
  ],
  "uncovered_queries": [],
  "analysis": {
    "topic": "sarjapur road",
    "competitor_summary": [
      {
        "competitor": "magicbricks.com",
        "result_count": 9,
        "depth": "hub",
        "strengths": "Dominant presence across all query types (listings, reviews, lifestyle content). Strong blog authority with lifestyle/investment angle. Comprehensive overview pages and ratings/reviews sections.",
        "weaknesses": "Generic listing pages with limited differentiation. Blog content lacks local micro-insights and recent market data. No specialized content on investment ROI or neighborhood micro-segments."
      },
      {
        "competitor": "99acres.com",
        "result_count": 9,
        "depth": "hub",
        "strengths": "Highest inventory visibility (2191+ apartments, 781+ 2BHK units). Strong presence in transactional queries. Ratings & reviews section captures user-generated trust signals.",
        "weaknesses": "Purely listing-focused; minimal editorial/lifestyle content. No thought leadership on area trends, investment thesis, or lifestyle guides. Relies on volume rather than depth."
      },
      {
        "competitor": "nobroker.in",
        "result_count": 8,
        "depth": "listing",
        "strengths": "Solid coverage of transactional queries (2BHK, flats for sale). Direct property listing pages rank well for high-intent keywords.",
        "weaknesses": "Minimal lifestyle, review, or informational content. No blog presence in sample results. Limited coverage of area overview and investment guidance."
      },
      {
        "competitor": "housing.com",
        "result_count": 1,
        "depth": "thin",
        "strengths": "Established brand; likely has listings but underperforming in Sarjapur Road SERP visibility.",
        "weaknesses": "Severely underrepresented in top 10 results across all probe queries. No meaningful content depth or authority signals for this locality."
      }
    ],
    "coverage_gaps": [
      {
        "gap": "Investment analysis & ROI projections for Sarjapur Road (price trends, appreciation potential, rental yields)",
        "priority": "high",
        "suggested_article_type": "hub"
      },
      {
        "gap": "Neighborhood micro-guides (sub-areas: Sarjapur Village, Sarjapur Main Road, Sarjapur Cross Road; amenities, schools, connectivity)",
        "priority": "high",
        "suggested_article_type": "hub"
      },
      {
        "gap": "Buyer's guide: First-time homebuyer checklist for Sarjapur Road (legal, registration, builder reputation)",
        "priority": "high",
        "suggested_article_type": "spoke"
      },
      {
        "gap": "Comparative analysis: Sarjapur Road vs. adjacent localities (Whitefield, Marathahalli, Bellandur) for investment/lifestyle",
        "priority": "medium",
        "suggested_article_type": "spoke"
      },
      {
        "gap": "Infrastructure & connectivity deep-dive (metro expansion, road projects, traffic patterns, commute times to IT hubs)",
        "priority": "medium",
        "suggested_article_type": "spoke"
      },
      {
        "gap": "Developer profiles & project reviews (Canvas Homes projects, competitor projects, quality benchmarks)",
        "priority": "medium",
        "suggested_article_type": "sub_spoke"
      },
      {
        "gap": "Lifestyle & community content (restaurants, gyms, parks, schools, healthcare; resident testimonials)",
        "priority": "medium",
        "suggested_article_type": "blog"
      },
      {
        "gap": "FAQ: Rental vs. purchase, property tax, maintenance costs, resale potential for Sarjapur Road",
        "priority": "low",
        "suggested_article_type": "faq"
      }
    ],
    "our_advantages": [
      "Local developer credibility: Canvas Homes can provide authentic project-level insights, quality benchmarks, and construction timelines competitors cannot match",
      "Data freshness: Real-time inventory, price updates, and market sentiment from Canvas Homes' own projects and local network vs. aggregated/stale competitor data",
      "Micro-locality expertise: Detailed neighborhood guides with Canvas Homes' on-ground knowledge of Sarjapur Road sub-segments, traffic patterns, and emerging amenities",
      "Investment thesis authority: Original ROI analysis, appreciation trends, and rental yield data tied to Canvas Homes' project performance and market research",
      "Buyer journey content: Specialized guides (legal, registration, builder selection) positioning Canvas Homes as trusted advisor, not just listing aggregator",
      "Community & lifestyle narrative: Authentic resident stories and lifestyle content from Canvas Homes communities, differentiating from generic competitor reviews"
    ],
    "summary": "Sarjapur Road is dominated by listing-heavy competitors (99acres, magicbricks, nobroker) with strong transactional coverage but minimal editorial depth or local expertise. Canvas Homes can win by creating authoritative investment guides, neighborhood micro-content, buyer education, and authentic developer/community narratives that competitors cannot replicate."
  },
  "summary": "'sarjapur road': magicbricks=9, nobroker=8, housing=1, 99acres=9 | 0 uncovered | 8 gaps identified"
}